Workbook
Name opc: Invst!$D$24:$D$24

Sheet Invst
B2: INVESTIMENTOS
B5: Configurações
B6: Salário | D6: 5000
B7: Rendimento da carteira | D7: 0.0089
B8: Sugestão de investimento | D8: =D6*30% -> 1500
B10: Investimento mensal
B11: Investimento mensal? | D11: 600
B12: Anos de investimento? | D12: 7
B13: Taxa de rendimentos mensal? | D13: 0.01079
B14: Patrimônio acumulado? | D14: =FV(D13,D12*12,D11*-1) -> 81370.22
B15: Dividendos mensais? | D15: =D14*1% -> 813.7022
E16: 2
B17: Cenários | D17: Dividendos | E17: 5
A18: 2 | B18: Quanto em 2 anos? | C18: =FV($D$13,$A18*12,$D$11*-1) -> 16336.576 | D18: =C18*$D$7 -> 145.39553 | E18: 10
A19: 5 | B19: Quanto em 5 anos? | C19: =FV($D$13,$A19*12,$D$11*-1) -> 50266.148 | D19: =C19*$D$7 -> 447.36872 | E19: 20
A20: 10 | B20: Quanto em 10 anos? | C20: =FV($D$13,$A20*12,$D$11*-1) -> 145970.53 | D20: =C20*$D$7 -> 1299.1377 | E20: 30
A21: 20 | B21: Quanto em 20 anos? | C21: =FV($D$13,$A21*12,$D$11*-1) -> 675119.04 | D21: =C21*$D$7 -> 6008.5595
A22: 30 | B22: Quanto em 30 anos? | C22: =FV($D$13,$A22*12,$D$11*-1) -> 2593301.8 | D22: =C22*$D$7 -> 23080.386
B24: Perfil | D24: Conservador
B25: Valor a ser investido por mês | D25: =D11 -> 600
B27: Tipo de FII | C27: Percentual sugerido | D27: Valores
B28: PAPEL | C28: =VLOOKUP($D$24&"-"&B28,aux!$A:$D,4,FALSE) -> 0.3 | D28: =$D$25*C28 -> 180
B29: TIJOLO | C29: =VLOOKUP($D$24&"-"&B29,aux!$A:$D,4,FALSE) -> 0.5 | D29: =$D$25*C29 -> 300
B30: HÏBRIDO | C30: =VLOOKUP($D$24&"-"&B30,aux!$A:$D,4,FALSE) -> 0.1 | D30: =$D$25*C30 -> 60
B31: FOFs | C31: =VLOOKUP($D$24&"-"&B31,aux!$A:$D,4,FALSE) -> 0.1 | D31: =$D$25*C31 -> 60
B32: DESENVOLVIMENTO | C32: =VLOOKUP($D$24&"-"&B32,aux!$A:$D,4,FALSE) -> 0 | D32: =$D$25*C32 -> 0
B33: HOTELARIAS | C33: =VLOOKUP($D$24&"-"&B33,aux!$A:$D,4,FALSE) -> 0 | D33: =$D$25*C33 -> 0
D34: =SUM(D28:D33) -> 600

Sheet aux
A1: Chave | B1: Perfil | C1: Tipo de FII | D1: %
A2: =B2&"-"&C2 -> Conservador-PAPEL | B2: Conservador | C2: PAPEL | D2: 0.3
A3: =B3&"-"&C3 -> Conservador-TIJOLO | B3: Conservador | C3: TIJOLO | D3: 0.5
A4: =B4&"-"&C4 -> Conservador-HÏBRIDO | B4: Conservador | C4: HÏBRIDO | D4: 0.1
A5: =B5&"-"&C5 -> Conservador-FOFs | B5: Conservador | C5: FOFs | D5: 0.1
A6: =B6&"-"&C6 -> Conservador-DESENVOLVIMENTO | B6: Conservador | C6: DESENVOLVIMENTO | D6: 0
A7: =B7&"-"&C7 -> Conservador-HOTELARIAS | B7: Conservador | C7: HOTELARIAS | D7: 0
A8: =B8&"-"&C8 -> Moderado-PAPEL | B8: Moderado | C8: PAPEL | D8: 0.32
A9: =B9&"-"&C9 -> Moderado-TIJOLO | B9: Moderado | C9: TIJOLO | D9: 0.3
A10: =B10&"-"&C10 -> Moderado-HÏBRIDO | B10: Moderado | C10: HÏBRIDO | D10: 0.08
A11: =B11&"-"&C11 -> Moderado-FOFs | B11: Moderado | C11: FOFs | D11: 0.1
A12: =B12&"-"&C12 -> Moderado-DESENVOLVIMENTO | B12: Moderado | C12: DESENVOLVIMENTO | D12: 0.1
A13: =B13&"-"&C13 -> Moderado-HOTELARIAS | B13: Moderado | C13: HOTELARIAS | D13: 0.1
... A19: =B19&"-"&C19 -> Agressivo-HOTELARIAS | B19: Agressivo | C19: HOTELARIAS | D19: 0.1
